LICENSE
README.md
setup.py
mlcakes/__init__.py
mlcakes.egg-info/PKG-INFO
mlcakes.egg-info/SOURCES.txt
mlcakes.egg-info/dependency_links.txt
mlcakes.egg-info/requires.txt
mlcakes.egg-info/top_level.txt
mlcakes/evaluation/__init__.py
mlcakes/evaluation/binary_class.py
mlcakes/evaluation/multi_class.py