Metadata-Version: 2.1
Name: mlcakes
Version: 0.0.6
Summary: Some functional modules for machine learning.
Author: Billy
Author-email: liangbilin0324@163.com
License: UNKNOWN
Platform: UNKNOWN
Requires-Python: >=3.9.*
License-File: LICENSE
